PathTraverser/Traverser.py
PathTraverser/__init__.py
PathTraverser/filters/Attributes.py
PathTraverser/filters/Call.py
PathTraverser/filters/Depth.py
PathTraverser/filters/Extension.py
PathTraverser/filters/Generic.py
PathTraverser/filters/Name.py
PathTraverser/filters/Path.py
PathTraverser/filters/PathType.py
PathTraverser/filters/__init__.py
PathTraverser/utils/Os.py
PathTraverser/utils/Path.py
PathTraverser/utils/__init__.py
pathtraverser-2.0.0.dist-info/METADATA
pathtraverser-2.0.0.dist-info/WHEEL
pathtraverser-2.0.0.dist-info/licenses/LICENSE
pathtraverser-2.0.0.dist-info/RECORD
