Metadata-Version: 2.1
Name: PathTraverser
Version: 2.0.0
Summary: Traversing file system in Python easily
Keywords: traverse,walk,list,files,directories,dirs,filesystem,path,paths
Home-page: https://github.com/htarnacki/PathTraverser
Author-Email: Hubert Tarnacki <hubert.tarnacki@gmail.com>
Maintainer-Email: Hubert Tarnacki <hubert.tarnacki@gmail.com>
License: MIT License
Classifier: Topic :: Software Development :: Libraries
Classifier: Topic :: Software Development :: Libraries :: Python Modules
Classifier: Topic :: System :: Filesystems
Classifier: Programming Language :: Python
Classifier: License :: OSI Approved :: MIT License
Classifier: Operating System :: OS Independent
Project-URL: Homepage, https://github.com/htarnacki/PathTraverser
Project-URL: Repository, https://github.com/htarnacki/PathTraverser
Project-URL: Bug tracker, https://github.com/htarnacki/PathTraverser/issues
Requires-Python: >=3.12
